{
  "main": {
    "name":"Barry Tran",
    "location": "Vancouver, BC",
    "image":"profile_picture.jpg",
    "bio":[
      "I'm a Software Developer based in Vancouver, BC.",
      "My current area of expertise is Backend Development and DevOps for distributed systems, particularly with Microsoft Azure. I'm involved in all parts of the development cycle (design, development, production support).",
      "In addition to development, I take on leadership roles for my teams such as project planning and mentoring. I am currently the Scrum Master of my team.",
      "In the past, I have been a service reliability engineer and an SDET.",
      "Thanks for taking time to view my personal site."
    ],
    "email": "tran.barry.bat060@gmail.com",
    "social":[
      {
        "name":"linkedin",
        "url":"https://www.linkedin.com/in/barry-tran-a70b2180",
        "className":"fa fa-linkedin"
      },
      {
        "name":"github",
        "url":"https://github.com/tran-barry",
        "className":"fa fa-github"
      }
    ]
  },
  "resume":{
    "work":[
      {
        "company":"iQmetrix",
        "title":"Software Developer - API",
        "years":"2017 - Present",
        "description":"Design and develop solutions to align iQMetrix' APIs. Also facilitated agile practices as Scrum Master and provided mentorship for junior developers."
      },
      {
        "company":"iQmetrix",
        "title":"Software Developer - DevOps",
        "years":"2015 - 2017",
        "description":"Provided scripts and templates to automate all parts of the build and deployment pipeline. Also provided monitoring solutions and production support for multiple services."
      },
      {
        "company":"iQmetrix",
        "title":"Software Developer - SDET",
        "years":"2014 - 2015",
        "description":"Maintained UI tests for a large WPF application. Developed custom UI testing framework for test stability."
      }
    ],
    "skills":[
      {
        "parentSkillName":"Programming Languages",
        "childSkills": "C#, Powershell, Python, Ruby"
      },
      {
        "parentSkillName":"Data",
        "childSkills": "NoSQL, SQL"
      },
      {
        "parentSkillName":"Development Tools",
        "childSkills": "Docker, Git, MSBuild, MSDeploy, TeamCity, VSTS/TFS"
      },
      {
        "parentSkillName":"Service Reliability Tools",
        "childSkills": "HostedGraphite, NewRelic, PagerDuty, SCOM"
      },
      {
        "parentSkillName":"Microsoft Azure Services",
        "childSkills": "APIManagement, Application Insights, ARM Templates, Blob Storage, Cloud Service, CosmosDB, Event Hub, Web App, Functions, Linux Web App, Service Bus, Table Storage, Traffic Manager"
      }
    ],
    "education":[
      {
        "school":"Scrum Alliance",
        "degree":"Certified Scrum Master",
        "graduated":"2017"
      },
      {
        "school":"University of Saskatchewan",
        "degree":"B.E. in Engineering Physics",
        "graduated":"2013"
      },
      {
        "school":"University of Saskatchewan",
        "degree":"B.Sc. in Computer Science",
        "graduated":"2013"
      }
    ]
  },
  "extras":{
    "extras":[
      {
        "header":"Video Games",
        "text":"I'm passionate about video games - both playing and developing them. I've participated in multiple Game Jams, and regularly learn about designing them in my spare time."
      },
      {
        "header":"Figure Skating",
        "text":"In my youth, I competed at the national level for Figure Skating."
      }
    ]
  }
}
